setup_py_upgrade.py
setup_py_upgrade-1.3.1.dist-info/LICENSE
setup_py_upgrade-1.3.1.dist-info/METADATA
setup_py_upgrade-1.3.1.dist-info/WHEEL
setup_py_upgrade-1.3.1.dist-info/entry_points.txt
setup_py_upgrade-1.3.1.dist-info/top_level.txt
setup_py_upgrade-1.3.1.dist-info/RECORD
