Metadata-Version: 2.1
Name: setup_py_upgrade
Version: 1.3.1
Summary: upgrade a setup.py to declarative metadata
Home-page: https://github.com/asottile/setup-py-upgrade
Author: Anthony Sottile
Author-email: asottile@umich.edu
License: MIT
Classifier: License :: OSI Approved :: MIT License
Classifier: Programming Language :: Python :: 3
Classifier: Programming Language :: Python :: 3 :: Only
Classifier: Programming Language :: Python :: Implementation :: CPython
Requires-Python: >=3.8
License-File: LICENSE
